FdoJarParcial2/FdoJarParcial2.py
FdoJarParcial2/__init__.py
FdoJarParcial2-0.1.10.dist-info/METADATA
FdoJarParcial2-0.1.10.dist-info/WHEEL
FdoJarParcial2-0.1.10.dist-info/top_level.txt
FdoJarParcial2-0.1.10.dist-info/RECORD
