Metadata-Version: 2.1
Name: FdoJarParcial2
Version: 0.1.10
Summary: Suavizado de curvas
Home-page: https://gitlab.com/juanf.jaramillo1/curso-fci-2023-2.git
Author: Fernando Jaramillo
Author-email: juanf.jaramillo@udea.edu.co
License: MIT
